shortterm_memory/ChatbotMemory.py
shortterm_memory/__init__.py
shortterm_memory-1.1.2.dist-info/LICENSE
shortterm_memory-1.1.2.dist-info/METADATA
shortterm_memory-1.1.2.dist-info/WHEEL
shortterm_memory-1.1.2.dist-info/top_level.txt
shortterm_memory-1.1.2.dist-info/RECORD
