Metadata-Version: 2.2
Name: shortterm-memory
Version: 1.1.2
Summary: Une approche pour la gestion de la mémoire à court terme dans les chatbots.
Home-page: https://github.com/sebDtSci/ShortTerm-memory
Author: Tadiello Sébastien
Author-email: sebastientadiello@gmail.com
Classifier: Programming Language :: Python :: 3
Classifier: License :: OSI Approved :: MIT License
Classifier: Operating System :: OS Independent
Requires-Python: >=3.9
License-File: LICENSE
Requires-Dist: torch==2.4.0
Requires-Dist: transformers<5.0,>=4.44.1
Dynamic: author
Dynamic: author-email
Dynamic: classifier
Dynamic: description
Dynamic: description-content-type
Dynamic: home-page
Dynamic: requires-dist
Dynamic: requires-python
Dynamic: summary
